semver_gitlab_dfx_test/__init__.py
semver_gitlab_dfx_test/__main__.py
semver_gitlab_dfx_test/cli.py
semver_gitlab_dfx_test/constants.py
semver_gitlab_dfx_test/semver_dfx.py
semver_gitlab_dfx_test-0.0.1.dist-info/METADATA
semver_gitlab_dfx_test-0.0.1.dist-info/WHEEL
semver_gitlab_dfx_test-0.0.1.dist-info/top_level.txt
semver_gitlab_dfx_test-0.0.1.dist-info/RECORD
