Metadata-Version: 2.1
Name: semver-gitlab-dfx-test
Version: 0.0.1
Summary: Gitlab SEMVER Calculation CLI
Home-page: https://teamdefinex.com/
Author: DefineX Labs
Author-email: labs@teamdefinex.com.com
License: MIT
Keywords: semver semantic versioning
Platform: any
Classifier: Programming Language :: Python :: 3
Classifier: License :: OSI Approved :: MIT License
Classifier: Operating System :: OS Independent
Requires-Python: >=3.9
Requires-Dist: semver (==2.8.1)
Requires-Dist: python-gitlab (==3.1.0)
Requires-Dist: ddt (==1.4.4)
